prompt_fence/__init__.py
prompt_fence/_core.cpython-313-darwin.so
prompt_fence/_core.pyi
prompt_fence/builder.py
prompt_fence/types.py
prompt_fence-0.2.1.dist-info/METADATA
prompt_fence-0.2.1.dist-info/WHEEL
prompt_fence-0.2.1.dist-info/RECORD
