Metadata-Version: 2.4
Name: prompt-fence
Version: 0.2.1
Classifier: Development Status :: 4 - Beta
Classifier: Intended Audience :: Developers
Classifier: License :: OSI Approved :: MIT License
Classifier: Programming Language :: Python :: 3
Classifier: Programming Language :: Python :: 3.9
Classifier: Programming Language :: Python :: 3.10
Classifier: Programming Language :: Python :: 3.11
Classifier: Programming Language :: Python :: 3.12
Classifier: Programming Language :: Python :: 3.13
Classifier: Programming Language :: Rust
Classifier: Topic :: Security :: Cryptography
Classifier: Topic :: Scientific/Engineering :: Artificial Intelligence
Summary: Python SDK for Prompt Fence - cryptographic security boundaries for LLM prompts
Keywords: llm,prompt-injection,security,cryptography,ai-safety
License: MIT
Requires-Python: >=3.9, <3.14
